{"stats":{"minecraft:mined":{"minecraft:spruce_planks":4,"minecraft:oak_sapling":14,"minecraft:white_bed":9,"minecraft:farmland":22,"minecraft:brewing_stand":6,"minecraft:obsidian":37,"minecraft:spruce_trapdoor":2,"minecraft:granite":1562,"minecraft:acacia_log":23,"minecraft:grass_block":706,"minecraft:cracked_polished_blackstone_bricks":10,"minecraft:oak_pressure_plate":1,"minecraft:crimson_fungus":31,"minecraft:oak_wall_sign":5,"minecraft:oxeye_daisy":48,"minecraft:gilded_blackstone":6,"minecraft:polished_blackstone_bricks":26,"minecraft:smooth_stone":8,"minecraft:weeping_vines_plant":24,"minecraft:magma_block":647,"minecraft:glowstone":103,"minecraft:iron_ore":2180,"minecraft:barrel":5,"minecraft:fire":16,"minecraft:pumpkin":91,"minecraft:anvil":3,"minecraft:azure_bluet":45,"minecraft:dark_oak_stairs":1,"minecraft:enchanting_table":2,"minecraft:red_tulip":38,"minecraft:oak_sign":3,"minecraft:oak_stairs":85,"minecraft:spruce_pressure_plate":2,"minecraft:pink_tulip":43,"minecraft:granite_stairs":53,"minecraft:brown_mushroom":38,"minecraft:quartz_block":7,"minecraft:blackstone":205,"minecraft:crimson_nylium":34,"minecraft:smoker":2,"minecraft:clay":55,"minecraft:torch":378,"minecraft:blast_furnace":2,"minecraft:poppy":88,"minecraft:chest":27,"minecraft:glass":2,"minecraft:cobblestone":649,"minecraft:nether_quartz_ore":1512,"minecraft:oak_planks":54,"minecraft:sugar_cane":254,"minecraft:grindstone":2,"minecraft:wall_torch":460,"minecraft:cauldron":1,"minecraft:birch_sapling":5,"minecraft:chain":26,"minecraft:warped_nylium":16,"minecraft:powered_rail":1,"minecraft:nether_wart_block":75,"minecraft:birch_log":231,"minecraft:wheat":542,"minecraft:lilac":51,"minecraft:warped_fungus":40,"minecraft:pumpkin_stem":10,"minecraft:orange_tulip":65,"minecraft:grass":2278,"minecraft:oak_log":802,"minecraft:beetroots":197,"minecraft:oak_fence_gate":4,"minecraft:sand":256,"minecraft:dirt":1321,"minecraft:crimson_planks":4,"minecraft:ancient_debris":2,"minecraft:netherrack":13276,"minecraft:oak_leaves":886,"minecraft:nether_gold_ore":264,"minecraft:diamond_ore":182,"minecraft:red_carpet":111,"minecraft:oak_door":4,"minecraft:ladder":8,"minecraft:black_banner":12,"minecraft:spruce_fence":35,"minecraft:crimson_roots":2,"minecraft:weeping_vines":17,"minecraft:redstone_wire":2,"minecraft:spruce_leaves":609,"minecraft:red_mushroom":41,"minecraft:crimson_stem":66,"minecraft:large_fern":16,"minecraft:hay_block":2,"minecraft:oak_trapdoor":1,"minecraft:redstone_ore":1830,"minecraft:spruce_sapling":1,"minecraft:furnace":19,"minecraft:carrots":185,"minecraft:nether_sprouts":1,"minecraft:andesite":1170,"minecraft:peony":63,"minecraft:bell":1,"minecraft:bookshelf":9,"minecraft:potatoes":274,"minecraft:shroomlight":10,"minecraft:vine":326,"minecraft:rail":31,"minecraft:lantern":37,"minecraft:white_tulip":41,"minecraft:stone":22819,"minecraft:redstone_wall_torch":2,"minecraft:oak_slab":158,"minecraft:glass_pane":2,"minecraft:soul_sand":140,"minecraft:lily_of_the_valley":6,"minecraft:basalt":205,"minecraft:dandelion":110,"minecraft:spruce_door":2,"minecraft:oak_fence":120,"minecraft:crafting_table":34,"minecraft:cornflower":76,"minecraft:emerald_ore":29,"minecraft:warped_roots":21,"minecraft:rose_bush":67,"minecraft:campfire":2,"minecraft:tall_grass":83,"minecraft:lapis_ore":259,"minecraft:diorite":1541,"minecraft:warped_wart_block":47,"minecraft:spruce_stairs":12,"minecraft:beehive":15,"minecraft:redstone_torch":2,"minecraft:black_wall_banner":12,"minecraft:sweet_berry_bush":59,"minecraft:birch_leaves":324,"minecraft:spruce_log":189,"minecraft:bee_nest":2,"minecraft:grass_path":29,"minecraft:coal_ore":5689,"minecraft:flower_pot":1,"minecraft:sunflower":1,"minecraft:gravel":891,"minecraft:gray_carpet":90,"minecraft:cobweb":101,"minecraft:gold_ore":575,"minecraft:infested_stone":21,"minecraft:fern":29},"minecraft:dropped":{"minecraft:iron_sword":1,"minecraft:brown_mushroom":2,"minecraft:porkchop":5,"minecraft:crafting_table":3,"minecraft:leather":1,"minecraft:spruce_leaves":10,"minecraft:cracked_polished_blackstone_bricks":11,"minecraft:dirt":97,"minecraft:grass":5,"minecraft:seagrass":2,"minecraft:polished_blackstone_bricks":20,"minecraft:acacia_door":2,"minecraft:white_wool":8,"minecraft:gravel":162,"minecraft:stone_axe":2,"minecraft:blackstone":3,"minecraft:golden_chestplate":1,"minecraft:rotten_flesh":309,"minecraft:oak_planks":1,"minecraft:rabbit_foot":1,"minecraft:chainmail_chestplate":1,"minecraft:poppy":1,"minecraft:rabbit_hide":3,"minecraft:leather_chestplate":1,"minecraft:beetroot_seeds":8,"minecraft:chainmail_boots":1,"minecraft:leather_boots":2,"minecraft:chest":1,"minecraft:leather_leggings":1,"minecraft:netherrack":7483,"minecraft:crimson_planks":4,"minecraft:golden_boots":1,"minecraft:wheat_seeds":232,"minecraft:golden_helmet":1,"minecraft:poisonous_potato":2,"minecraft:cobblestone":12489,"minecraft:granite":535,"minecraft:spruce_stairs":2,"minecraft:chainmail_helmet":1,"minecraft:coal":236,"minecraft:gray_wool":1,"minecraft:diorite":637,"minecraft:brewing_stand":1,"minecraft:pumpkin":11,"minecraft:iron_axe":1,"minecraft:smooth_stone":6,"minecraft:iron_shovel":5,"minecraft:paper":5,"minecraft:gray_carpet":76,"minecraft:spruce_sapling":3,"minecraft:redstone_block":39,"minecraft:redstone":1375,"minecraft:pink_tulip":1,"minecraft:kelp":5,"minecraft:stone_sword":2,"minecraft:shears":1,"minecraft:pumpkin_seeds":16,"minecraft:filled_map":2,"minecraft:potato":2,"minecraft:spruce_planks":2,"minecraft:andesite":404,"minecraft:golden_leggings":2,"minecraft:oak_sapling":106,"minecraft:golden_sword":1,"minecraft:spider_eye":1,"minecraft:spruce_log":12,"minecraft:bow":1,"minecraft:stone_pickaxe":1,"minecraft:magma_block":13},"minecraft:broken":{"minecraft:golden_helmet":1,"minecraft:iron_shovel":2,"minecraft:shears":3,"minecraft:stone_pickaxe":4,"minecraft:iron_sword":1,"minecraft:iron_hoe":1,"minecraft:iron_axe":5,"minecraft:iron_pickaxe":10},"minecraft:killed_by":{"minecraft:creeper":6,"minecraft:cave_spider":1,"minecraft:zombie":4,"minecraft:enderman":1,"minecraft:skeleton":1},"minecraft:picked_up":{"minecraft:seagrass":2,"minecraft:iron_chestplate":7,"minecraft:wheat":489,"minecraft:chainmail_boots":1,"minecraft:redstone_block":100,"minecraft:anvil":3,"minecraft:flower_pot":1,"minecraft:lead":11,"minecraft:oak_stairs":85,"minecraft:gilded_blackstone":6,"minecraft:crimson_planks":4,"minecraft:brewing_stand":7,"minecraft:golden_sword":3,"minecraft:lapis_block":80,"minecraft:string":250,"minecraft:iron_leggings":7,"minecraft:pufferfish":6,"minecraft:shroomlight":7,"minecraft:oak_sign":10,"minecraft:beetroot":169,"minecraft:gold_nugget":1162,"minecraft:smooth_stone":8,"minecraft:spruce_planks":4,"minecraft:white_tulip":38,"minecraft:rose_bush":66,"minecraft:redstone_torch":4,"minecraft:iron_pickaxe":7,"minecraft:iron_boots":7,"minecraft:furnace":19,"minecraft:golden_helmet":2,"minecraft:spruce_pressure_plate":2,"minecraft:beehive":15,"minecraft:stick":528,"minecraft:oak_fence":151,"minecraft:torch":1104,"minecraft:acacia_log":23,"minecraft:spruce_stairs":11,"minecraft:porkchop":38,"minecraft:diorite":1488,"minecraft:vine":251,"minecraft:golden_chestplate":1,"minecraft:rabbit_foot":1,"minecraft:cauldron":1,"minecraft:quartz_block":7,"minecraft:rotten_flesh":359,"minecraft:tropical_fish":4,"minecraft:red_tulip":37,"minecraft:obsidian":37,"minecraft:cod":16,"minecraft:cobblestone":22820,"minecraft:birch_log":231,"minecraft:enchanting_table":2,"minecraft:water_bucket":5,"minecraft:magma_block":501,"minecraft:leather_chestplate":1,"minecraft:feather":136,"minecraft:lilac":51,"minecraft:cooked_beef":59,"minecraft:magma_cream":3,"minecraft:andesite":1099,"minecraft:golden_leggings":4,"minecraft:smoker":2,"minecraft:potato":859,"minecraft:flint":123,"minecraft:light_gray_dye":1,"minecraft:acacia_boat":3,"minecraft:lapis_lazuli":1959,"minecraft:dirt":2034,"minecraft:lantern":41,"minecraft:leather_boots":2,"minecraft:bone":149,"minecraft:bow":16,"minecraft:wheat_seeds":1702,"minecraft:orange_tulip":64,"minecraft:bell":1,"minecraft:grindstone":2,"minecraft:diamond_helmet":1,"minecraft:powered_rail":1,"minecraft:rabbit":1,"minecraft:glowstone_dust":281,"minecraft:honeycomb":24,"minecraft:oak_planks":401,"minecraft:cooked_porkchop":4,"minecraft:warped_wart_block":47,"minecraft:oak_pressure_plate":1,"minecraft:poisonous_potato":2,"minecraft:birch_fence_gate":1,"minecraft:sand":248,"minecraft:ink_sac":16,"minecraft:lily_of_the_valley":6,"minecraft:barrel":5,"minecraft:iron_hoe":2,"minecraft:diamond":275,"minecraft:cracked_polished_blackstone_bricks":11,"minecraft:crossbow":1,"minecraft:granite":1457,"minecraft:grass":70,"minecraft:chainmail_helmet":2,"minecraft:emerald":40,"minecraft:oak_sapling":323,"minecraft:netherrack":9163,"minecraft:crimson_roots":2,"minecraft:diamond_pickaxe":1,"minecraft:fishing_rod":1,"minecraft:spruce_leaves":522,"minecraft:charcoal":4,"minecraft:crafting_table":33,"minecraft:azure_bluet":45,"minecraft:chicken":106,"minecraft:ladder":29,"minecraft:clay_ball":212,"minecraft:leather_leggings":1,"minecraft:brown_mushroom":39,"minecraft:chain":25,"minecraft:shield":5,"minecraft:cornflower":75,"minecraft:oak_trapdoor":1,"minecraft:iron_axe":1,"minecraft:iron_shovel":3,"minecraft:blackstone":163,"minecraft:beef":141,"minecraft:poppy":87,"minecraft:light_gray_wool":33,"minecraft:minecart":12,"minecraft:sugar_cane":482,"minecraft:chest":30,"minecraft:birch_sapling":77,"minecraft:spruce_trapdoor":2,"minecraft:egg":281,"minecraft:oak_door":14,"minecraft:bowl":1,"minecraft:spruce_fence":33,"minecraft:polished_blackstone_bricks":20,"minecraft:white_dye":3,"minecraft:carrot":504,"minecraft:redstone":7614,"minecraft:arrow":229,"minecraft:weeping_vines":40,"minecraft:beetroot_seeds":487,"minecraft:peony":62,"minecraft:hay_block":2,"minecraft:pink_tulip":43,"minecraft:black_banner":25,"minecraft:mutton":42,"minecraft:white_wool":76,"minecraft:rail":57,"minecraft:oxeye_daisy":48,"minecraft:basalt":188,"minecraft:crimson_stem":64,"minecraft:salmon":8,"minecraft:leather":124,"minecraft:fern":2,"minecraft:red_mushroom":40,"minecraft:granite_stairs":65,"minecraft:crimson_fungus":31,"minecraft:oak_log":799,"minecraft:chainmail_chestplate":1,"minecraft:ancient_debris":2,"minecraft:golden_boots":3,"minecraft:nether_wart_block":64,"minecraft:gunpowder":36,"minecraft:cooked_mutton":47,"minecraft:red_carpet":113,"minecraft:apple":39,"minecraft:gray_carpet":90,"minecraft:kelp":5,"minecraft:rabbit_hide":3,"minecraft:iron_ingot":24,"minecraft:oak_fence_gate":4,"minecraft:cooked_chicken":50,"minecraft:iron_ore":2472,"minecraft:glass_bottle":4,"minecraft:iron_sword":10,"minecraft:soul_sand":139,"minecraft:dark_oak_stairs":1,"minecraft:book":27,"minecraft:oak_slab":173,"minecraft:warped_fungus":38,"minecraft:pumpkin":90,"minecraft:sweet_berries":143,"minecraft:quartz":1775,"minecraft:dandelion":114,"minecraft:gravel":761,"minecraft:spruce_sapling":11,"minecraft:blast_furnace":2,"minecraft:white_bed":9,"minecraft:spruce_log":192,"minecraft:gold_ore":697,"minecraft:spider_eye":27,"minecraft:spruce_door":2,"minecraft:pumpkin_seeds":13,"minecraft:slime_ball":11,"minecraft:iron_helmet":7,"minecraft:painting":59,"minecraft:gray_wool":87,"minecraft:warped_roots":20,"minecraft:black_wool":59,"minecraft:coal":6220,"minecraft:ender_pearl":6},"minecraft:crafted":{"minecraft:brick":5,"minecraft:grindstone":1,"minecraft:smooth_stone":9,"minecraft:oak_planks":2272,"minecraft:oak_sign":9,"minecraft:cobblestone_slab":6,"minecraft:barrel":6,"minecraft:oak_pressure_plate":2,"minecraft:cooked_chicken":100,"minecraft:chain":27,"minecraft:stone":786,"minecraft:bookshelf":23,"minecraft:spruce_pressure_plate":1,"minecraft:cooked_mutton":30,"minecraft:quartz_block":432,"minecraft:glass":93,"minecraft:diamond_leggings":2,"minecraft:diamond_helmet":2,"minecraft:bow":5,"minecraft:iron_boots":1,"minecraft:birch_fence_gate":1,"minecraft:chest":30,"minecraft:rail":304,"minecraft:magenta_dye":2,"minecraft:oak_fence":423,"minecraft:cooked_rabbit":1,"minecraft:flower_pot":1,"minecraft:granite_stairs":104,"minecraft:smoker":1,"minecraft:glass_bottle":21,"minecraft:oak_slab":306,"minecraft:arrow":64,"minecraft:cauldron":1,"minecraft:cooked_porkchop":26,"minecraft:map":3,"minecraft:crafting_table":14,"minecraft:spruce_planks":212,"minecraft:wooden_pickaxe":3,"minecraft:iron_helmet":1,"minecraft:baked_potato":144,"minecraft:spruce_door":3,"minecraft:red_wool":52,"minecraft:gold_block":72,"minecraft:hay_block":23,"minecraft:pumpkin_seeds":44,"minecraft:birch_planks":84,"minecraft:campfire":1,"minecraft:painting":4,"minecraft:spruce_trapdoor":4,"minecraft:iron_chestplate":1,"minecraft:book":47,"minecraft:paper":234,"minecraft:diamond_pickaxe":13,"minecraft:yellow_dye":16,"minecraft:shield":1,"minecraft:stick":1152,"minecraft:stone_slab":6,"minecraft:compass":3,"minecraft:iron_ingot":2352,"minecraft:iron_pickaxe":13,"minecraft:iron_block":207,"minecraft:stone_sword":3,"minecraft:acacia_door":3,"minecraft:gold_ingot":770,"minecraft:black_bed":1,"minecraft:light_gray_dye":18,"minecraft:gray_carpet":78,"minecraft:redstone_torch":65,"minecraft:shears":5,"minecraft:oak_door":15,"minecraft:redstone":63,"minecraft:coal":153,"minecraft:fishing_rod":1,"minecraft:beehive":6,"minecraft:iron_nugget":628,"minecraft:furnace":9,"minecraft:blast_furnace":1,"minecraft:bone_meal":141,"minecraft:spruce_fence":63,"minecraft:pink_dye":19,"minecraft:vine":4,"minecraft:oak_trapdoor":6,"minecraft:glass_pane":64,"minecraft:flint_and_steel":1,"minecraft:terracotta":4,"minecraft:lantern":66,"minecraft:spruce_stairs":4,"minecraft:iron_axe":10,"minecraft:ladder":39,"minecraft:iron_hoe":3,"minecraft:stone_pickaxe":6,"minecraft:diamond_boots":2,"minecraft:filled_map":8,"minecraft:redstone_block":622,"minecraft:netherite_scrap":2,"minecraft:minecart":13,"minecraft:cooked_beef":138,"minecraft:coal_block":445,"minecraft:red_dye":68,"minecraft:diamond_sword":4,"minecraft:enchanting_table":1,"minecraft:powered_rail":60,"minecraft:iron_sword":3,"minecraft:black_banner":1,"minecraft:bucket":2,"minecraft:red_carpet":78,"minecraft:stone_axe":3,"minecraft:glowstone":69,"minecraft:orange_dye":19,"minecraft:acacia_boat":1,"minecraft:bread":15,"minecraft:blue_dye":14,"minecraft:beetroot_seeds":5,"minecraft:oak_fence_gate":13,"minecraft:oak_boat":1,"minecraft:gold_nugget":46,"minecraft:white_dye":3,"minecraft:oak_stairs":216,"minecraft:wooden_axe":3,"minecraft:iron_shovel":8,"minecraft:iron_leggings":1,"minecraft:anvil":3,"minecraft:white_bed":1,"minecraft:acacia_planks":92,"minecraft:torch":1938,"minecraft:lapis_lazuli":9,"minecraft:lapis_block":177,"minecraft:clay":40,"minecraft:diamond_chestplate":2},"minecraft:killed":{"minecraft:cave_spider":5,"minecraft:zombified_piglin":9,"minecraft:witch":2,"minecraft:spider":60,"minecraft:skeleton":108,"minecraft:chicken":159,"minecraft:silverfish":24,"minecraft:turtle":1,"minecraft:magma_cube":131,"minecraft:wolf":3,"minecraft:piglin":43,"minecraft:pig":3,"minecraft:zombie_villager":7,"minecraft:creeper":36,"minecraft:sheep":39,"minecraft:trader_llama":8,"minecraft:zombie":317,"minecraft:ghast":1,"minecraft:stray":1,"minecraft:cow":88,"minecraft:slime":16,"minecraft:llama":2,"minecraft:drowned":12,"minecraft:rabbit":3,"minecraft:bat":2,"minecraft:wandering_trader":1,"minecraft:hoglin":13,"minecraft:squid":3,"minecraft:enderman":13},"minecraft:used":{"minecraft:peony":7,"minecraft:iron_shovel":1764,"minecraft:oak_sign":16,"minecraft:ladder":36,"minecraft:poppy":8,"minecraft:chest":57,"minecraft:iron_sword":542,"minecraft:stone":276,"minecraft:grass":9,"minecraft:rotten_flesh":7,"minecraft:spruce_leaves":445,"minecraft:soul_sand":78,"minecraft:carrot":268,"minecraft:obsidian":16,"minecraft:beehive":21,"minecraft:weeping_vines":20,"minecraft:azure_bluet":17,"minecraft:glass":48,"minecraft:lantern":102,"minecraft:birch_sapling":61,"minecraft:quartz_block":227,"minecraft:red_carpet":191,"minecraft:magma_block":60,"minecraft:bow":127,"minecraft:hay_block":2,"minecraft:sweet_berries":56,"minecraft:oak_sapling":214,"minecraft:furnace":24,"minecraft:beetroot_seeds":250,"minecraft:egg":64,"minecraft:potato":349,"minecraft:diorite":171,"minecraft:oak_planks":146,"minecraft:spruce_door":5,"minecraft:stone_pickaxe":581,"minecraft:gray_carpet":92,"minecraft:powered_rail":37,"minecraft:orange_tulip":4,"minecraft:blackstone":1,"minecraft:wooden_pickaxe":63,"minecraft:sugar_cane":49,"minecraft:sand":23,"minecraft:blast_furnace":3,"minecraft:black_banner":26,"minecraft:pumpkin_seeds":41,"minecraft:black_bed":1,"minecraft:shears":844,"minecraft:redstone_torch":41,"minecraft:acacia_door":1,"minecraft:bread":19,"minecraft:oak_pressure_plate":1,"minecraft:gravel":17,"minecraft:lilac":5,"minecraft:diamond_sword":3021,"minecraft:nether_wart_block":3,"minecraft:grindstone":2,"minecraft:cooked_rabbit":1,"minecraft:andesite":146,"minecraft:chain":47,"minecraft:oak_boat":1,"minecraft:oak_fence":528,"minecraft:oak_trapdoor":6,"minecraft:bone_meal":49,"minecraft:stone_sword":182,"minecraft:white_tulip":4,"minecraft:granite_stairs":104,"minecraft:enchanting_table":3,"minecraft:flint_and_steel":1,"minecraft:redstone":2,"minecraft:cooked_chicken":62,"minecraft:netherrack":1146,"minecraft:oak_door":19,"minecraft:torch":2684,"minecraft:brewing_stand":6,"minecraft:dirt":1340,"minecraft:anvil":6,"minecraft:spruce_stairs":13,"minecraft:oak_fence_gate":17,"minecraft:granite":174,"minecraft:spruce_fence":88,"minecraft:fern":2,"minecraft:shroomlight":1,"minecraft:iron_hoe":647,"minecraft:wooden_axe":3,"minecraft:bookshelf":23,"minecraft:iron_axe":2719,"minecraft:oak_stairs":283,"minecraft:barrel":11,"minecraft:glowstone":4,"minecraft:basalt":61,"minecraft:minecart":11,"minecraft:cooked_beef":76,"minecraft:crimson_stem":3,"minecraft:wheat_seeds":574,"minecraft:cooked_mutton":40,"minecraft:acacia_boat":3,"minecraft:water_bucket":70,"minecraft:iron_ore":1,"minecraft:pink_tulip":7,"minecraft:baked_potato":122,"minecraft:brown_mushroom":4,"minecraft:cauldron":2,"minecraft:gilded_blackstone":2,"minecraft:vine":191,"minecraft:rail":258,"minecraft:crafting_table":43,"minecraft:oak_slab":450,"minecraft:red_mushroom":3,"minecraft:white_bed":8,"minecraft:campfire":1,"minecraft:painting":63,"minecraft:smoker":3,"minecraft:oak_log":48,"minecraft:flower_pot":2,"minecraft:cornflower":5,"minecraft:diamond_pickaxe":52315,"minecraft:oxeye_daisy":9,"minecraft:iron_pickaxe":2978,"minecraft:map":3,"minecraft:suspicious_stew":1,"minecraft:spruce_pressure_plate":3,"minecraft:spruce_trapdoor":2,"minecraft:spruce_sapling":8,"minecraft:stone_axe":170,"minecraft:fishing_rod":43,"minecraft:cobblestone":7162,"minecraft:cooked_porkchop":4,"minecraft:bucket":74,"minecraft:glass_pane":50,"minecraft:dandelion":26,"minecraft:smooth_stone":7},"minecraft:custom":{"minecraft:animals_bred":286,"minecraft:interact_with_crafting_table":540,"minecraft:open_barrel":448,"minecraft:leave_game":72,"minecraft:time_since_death":1854133,"minecraft:sprint_one_cm":3822804,"minecraft:drop":915,"minecraft:talked_to_villager":15,"minecraft:deaths":13,"minecraft:jump":15908,"minecraft:interact_with_brewingstand":3,"minecraft:walk_on_water_one_cm":536122,"minecraft:enchant_item":35,"minecraft:interact_with_furnace":322,"minecraft:traded_with_villager":9,"minecraft:play_one_minute":4604962,"minecraft:sleep_in_bed":136,"minecraft:damage_dealt":145026,"minecraft:crouch_one_cm":53749,"minecraft:interact_with_smoker":90,"minecraft:interact_with_smithing_table":1,"minecraft:use_cauldron":2,"minecraft:horse_one_cm":145232,"minecraft:interact_with_anvil":66,"minecraft:mob_kills":1144,"minecraft:fill_cauldron":4,"minecraft:climb_one_cm":81033,"minecraft:walk_one_cm":25321943,"minecraft:sneak_time":28690,"minecraft:walk_under_water_one_cm":105599,"minecraft:boat_one_cm":331130,"minecraft:interact_with_blast_furnace":208,"minecraft:pot_flower":1,"minecraft:interact_with_grindstone":13,"minecraft:time_since_rest":27046,"minecraft:damage_taken":19368,"minecraft:minecart_one_cm":303662,"minecraft:fly_one_cm":390200,"minecraft:open_chest":2366,"minecraft:fish_caught":34,"minecraft:fall_one_cm":130468}},"DataVersion":2580}